note/__init__.py
note/noted.py
note/schema.sql
note_board/__init__.py
note_board/noted.py
note_board/schema.sql
note_board-0.0.1.dist-info/LICENSE
note_board-0.0.1.dist-info/METADATA
note_board-0.0.1.dist-info/WHEEL
note_board-0.0.1.dist-info/entry_points.txt
note_board-0.0.1.dist-info/top_level.txt
note_board-0.0.1.dist-info/RECORD
